airbag/__init__.py
airbag-0.0.0.dist-info/LICENSE
airbag-0.0.0.dist-info/METADATA
airbag-0.0.0.dist-info/WHEEL
airbag-0.0.0.dist-info/top_level.txt
airbag-0.0.0.dist-info/RECORD
